[
  {
    "id": "ml:cc7b1d20c4",
    "label": "большие данные",
    "synonyms": [],
    "relations": {},
    "source": "termlint:ontology_update"
  },
  {
    "id": "ml:ba5d97c69d",
    "label": "глубокое обучение",
    "synonyms": [],
    "relations": {},
    "source": "termlint:ontology_update"
  },
  {
    "id": "ml:d1e2ef0910",
    "label": "искусственный интеллект",
    "synonyms": [],
    "relations": {},
    "source": "termlint:ontology_update"
  },
  {
    "id": "ml:daa31181fc",
    "label": "машинного обучения",
    "synonyms": [],
    "relations": {},
    "source": "termlint:ontology_update"
  },
  {
    "id": "ml:02a0087560",
    "label": "нейронные сети",
    "synonyms": [],
    "relations": {},
    "source": "termlint:ontology_update"
  }
]